{
	"id": "JXvR53YE8TF1TCs",
	"json": "{\"id\":\"JXvR53YE8TF1TCs\",\"url\":\"https://www.similarweb.com/blog/investor/asset-research/uk-grocery/\",\"loadedUrl\":\"https://www.similarweb.com/blog/investor/asset-research/uk-grocery/\",\"uniqueKey\":\"https://www.similarweb.com/blog/investor/asset-research/uk-grocery\",\"method\":\"GET\",\"noRetry\":false,\"retryCount\":0,\"errorMessages\":[],\"headers\":{},\"userData\":{\"enqueueTime\":1729722580099,\"__crawlee\":{\"enqueueStrategy\":\"same-domain\",\"state\":4}},\"handledAt\":\"2024-10-23T22:37:21.436Z\"}",
	"method": "GET",
	"orderNo": null,
	"retryCount": 0,
	"uniqueKey": "https://www.similarweb.com/blog/investor/asset-research/uk-grocery",
	"url": "https://www.similarweb.com/blog/investor/asset-research/uk-grocery/"
}