{
	"id": "SZVJ0fhqFE408iB",
	"json": "{\"id\":\"SZVJ0fhqFE408iB\",\"url\":\"https://moz.com/blog/seo-reports-with-storytelling\",\"loadedUrl\":\"https://moz.com/blog/seo-reports-with-storytelling\",\"uniqueKey\":\"https://moz.com/blog/seo-reports-with-storytelling\",\"method\":\"GET\",\"noRetry\":false,\"retryCount\":0,\"errorMessages\":[],\"headers\":{},\"userData\":{\"enqueueTime\":1729654429074,\"__crawlee\":{\"enqueueStrategy\":\"same-domain\",\"state\":4}},\"handledAt\":\"2024-10-23T03:45:34.319Z\"}",
	"method": "GET",
	"orderNo": null,
	"retryCount": 0,
	"uniqueKey": "https://moz.com/blog/seo-reports-with-storytelling",
	"url": "https://moz.com/blog/seo-reports-with-storytelling"
}