{
	"id": "uQXnromvwPFSUeC",
	"json": "{\"id\":\"uQXnromvwPFSUeC\",\"url\":\"https://moz.com/blog/the-real-power-of-twitter\",\"loadedUrl\":\"https://moz.com/blog/the-real-power-of-twitter\",\"uniqueKey\":\"https://moz.com/blog/the-real-power-of-twitter\",\"method\":\"GET\",\"noRetry\":false,\"retryCount\":0,\"errorMessages\":[],\"headers\":{},\"userData\":{\"enqueueTime\":1729663626497,\"__crawlee\":{\"enqueueStrategy\":\"same-domain\",\"state\":4}},\"handledAt\":\"2024-10-23T06:11:24.016Z\"}",
	"method": "GET",
	"orderNo": null,
	"retryCount": 0,
	"uniqueKey": "https://moz.com/blog/the-real-power-of-twitter",
	"url": "https://moz.com/blog/the-real-power-of-twitter"
}